[
  {
    "id": 1,
    "name": "Ahmed Hassan",
    "countryOfOrigin": "Egitto",
    "status": "Attivo",
    "health": "Visita programmata",
    "jobStatus": "In formazione",
    "bureaucracy": "Permesso in corso",
    "reviewer": "Maria Rossi"
  },
  {
    "id": 2,
    "name": "Fatima Al-Masri",
    "countryOfOrigin": "Siria",
    "status": "In Attesa",
    "health": "In trattamento",
    "jobStatus": "Disoccupato",
    "bureaucracy": "Residenza ottenuta",
    "reviewer": "Luca Bianchi"
  },
  {
    "id": 3,
    "name": "Mohamed Diallo",
    "countryOfOrigin": "Senegal",
    "status": "Attivo",
    "health": "OK",
    "jobStatus": "Occupato",
    "bureaucracy": "Permesso in corso",
    "reviewer": "Giulia Conti"
  },
  {
    "id": 4,
    "name": "Amina Kone",
    "countryOfOrigin": "Costa d'Avorio",
    "status": "Chiuso",
    "health": "OK",
    "jobStatus": "Occupato",
    "bureaucracy": "Residenza ottenuta",
    "reviewer": "Marco Esposito"
  },
  {
    "id": 5,
    "name": "Youssef Benali",
    "countryOfOrigin": "Marocco",
    "status": "Attivo",
    "health": "Visita programmata",
    "jobStatus": "In formazione",
    "bureaucracy": "Permesso in corso",
    "reviewer": "Maria Rossi"
  },
  {
    "id": 6,
    "name": "Sara Haddad",
    "countryOfOrigin": "Libano",
    "status": "In Attesa",
    "health": "In trattamento",
    "jobStatus": "Disoccupato",
    "bureaucracy": "Permesso in corso",
    "reviewer": "Luca Bianchi"
  },
  {
    "id": 7,
    "name": "Omar Farah",
    "countryOfOrigin": "Somalia",
    "status": "Attivo",
    "health": "OK",
    "jobStatus": "Occupato",
    "bureaucracy": "Residenza ottenuta",
    "reviewer": "Giulia Conti"
  },
  {
    "id": 8,
    "name": "Nadia El-Sayed",
    "countryOfOrigin": "Egitto",
    "status": "Chiuso",
    "health": "OK",
    "jobStatus": "Occupato",
    "bureaucracy": "Permesso in corso",
    "reviewer": "Marco Esposito"
  },
  {
    "id": 9,
    "name": "Ibrahim Diallo",
    "countryOfOrigin": "Mali",
    "status": "Attivo",
    "health": "Visita programmata",
    "jobStatus": "In formazione",
    "bureaucracy": "Permesso in corso",
    "reviewer": "Maria Rossi"
  },
  {
    "id": 10,
    "name": "Layla Ahmed",
    "countryOfOrigin": "Sudan",
    "status": "In Attesa",
    "health": "In trattamento",
    "jobStatus": "Disoccupato",
    "bureaucracy": "Residenza ottenuta",
    "reviewer": "Luca Bianchi"
  }
]
